MANIFEST.in
README.rst
setup.py
datetimezone_field/__init__.py
datetimezone_field/fields.py
datetimezone_field/widgets.py
django_datetimezone_field.egg-info/PKG-INFO
django_datetimezone_field.egg-info/SOURCES.txt
django_datetimezone_field.egg-info/dependency_links.txt
django_datetimezone_field.egg-info/requires.txt
django_datetimezone_field.egg-info/top_level.txt