Metadata-Version: 1.0
Name: django-datetimezone-field
Version: 0.1.3
Summary: A Django app providing database and form fields for split datetime/time and pytz timezone objects.
Home-page: https://github.com/GradConnection/django-datetimezone-field
Author: Eric Man
Author-email: eric@gradconnection.com
License: BSD
Platform: UNKNOWN
Classifier: Development Status :: 3 - Alpha
Classifier: Environment :: Web Environment
Classifier: Intended Audience :: Developers
Classifier: License :: OSI Approved :: BSD License
Classifier: Operating System :: OS Independent
Classifier: Programming Language :: Python
Classifier: Topic :: Utilities
Classifier: Framework :: Django
